{
    "assignments": [
        {
            "name": "Read chapter 4",
            "completed": false,
            "id": 1,
            "tag": "math"
        },
        {
            "name": "Turn in homework",
            "completed": false,
            "id": 2,
            "tag": "math"
        },
        {
            "name": "Finish project",
            "completed": false,
            "id": 3,
            "tag": "science"
        },
        {
            "name": "Fix the query",
            "completed": false,
            "id": 4,
            "tag": "programming"
        },
        {
            "name": "Memorize the laws",
            "completed": false,
            "id": 5,
            "tag": "physics"
        },
        {
            "name": "Finish the course",
            "completed": true,
            "id": 6,
            "tag": "programming"
        }
    ]
}
